zae_limiter/__init__.py
zae_limiter/bucket.py
zae_limiter/cli.py
zae_limiter/exceptions.py
zae_limiter/lease.py
zae_limiter/limiter.py
zae_limiter/models.py
zae_limiter/repository.py
zae_limiter/schema.py
zae_limiter/version.py
zae_limiter/aggregator/__init__.py
zae_limiter/aggregator/handler.py
zae_limiter/aggregator/processor.py
zae_limiter/infra/__init__.py
zae_limiter/infra/cfn_template.yaml
zae_limiter/infra/lambda_builder.py
zae_limiter/infra/stack_manager.py
zae_limiter/migrations/__init__.py
zae_limiter/migrations/v1_0_0.py
zae_limiter-0.1.0.dist-info/METADATA
zae_limiter-0.1.0.dist-info/WHEEL
zae_limiter-0.1.0.dist-info/entry_points.txt
zae_limiter-0.1.0.dist-info/licenses/LICENSE
zae_limiter-0.1.0.dist-info/RECORD
