Metadata-Version: 2.4
Name: zae-limiter
Version: 0.1.0
Summary: Rate limiting library backed by DynamoDB with token bucket algorithm
Project-URL: Homepage, https://github.com/zeroae/zae-limiter
Project-URL: Repository, https://github.com/zeroae/zae-limiter
Author-email: ZeroAE <dev@zeroae.com>
License: MIT License
License-File: LICENSE
Keywords: api-rate-limit,aws,dynamodb,llm,rate-limiting,token-bucket
Classifier: Development Status :: 3 - Alpha
Classifier: Intended Audience :: Developers
Classifier: License :: OSI Approved :: MIT License
Classifier: Programming Language :: Python :: 3
Classifier: Programming Language :: Python :: 3.11
Classifier: Programming Language :: Python :: 3.12
Classifier: Topic :: Software Development :: Libraries :: Python Modules
Requires-Python: >=3.11
Requires-Dist: aioboto3>=12.0.0
Requires-Dist: boto3>=1.34.0
Requires-Dist: click>=8.0.0
Requires-Dist: types-aiobotocore[dynamodb]>=2.0.0
Provides-Extra: cdk
Requires-Dist: aws-cdk-lib>=2.0.0; extra == 'cdk'
Requires-Dist: constructs>=10.0.0; extra == 'cdk'
Provides-Extra: dev
Requires-Dist: moto[dynamodb]>=5.0.0; extra == 'dev'
Requires-Dist: mypy>=1.8.0; extra == 'dev'
Requires-Dist: openapi-spec-validator>=0.7.1; extra == 'dev'
Requires-Dist: pytest-asyncio>=0.23.0; extra == 'dev'
Requires-Dist: pytest-cov>=4.0.0; extra == 'dev'
Requires-Dist: pytest>=8.0.0; extra == 'dev'
Requires-Dist: ruff>=0.1.0; extra == 'dev'
Provides-Extra: lambda
Requires-Dist: aws-lambda-powertools>=2.0.0; extra == 'lambda'
